curryparty/__init__.py
curryparty/core.py
curryparty/display.py
curryparty/py.typed
curryparty/utils.py
curryparty-0.2.2.dist-info/WHEEL
curryparty-0.2.2.dist-info/METADATA
curryparty-0.2.2.dist-info/RECORD
