Metadata-Version: 2.3
Name: curryparty
Version: 0.2.2
Summary: Python playground to learn lambda calculus
Author: Antonin P
Author-email: Antonin P <antonin.peronnet@telecom-paris.fr>
Requires-Dist: svg-py>=1.9.2
Requires-Python: >=3.13
